{
    "id": 1851,
    "audioText": "Tu payez joyeusement le capitaine pour ce bonheur instinctivement ressenti.",
    "question": "Tu payez joyeusement le capitaine pour ce bonheur instinctivement ressenti.",
    "questionType": "listening",
    "options": [
        "Tu paies joyeusement le capitaine pour ce bonheur instinctivement ressenti",
        "Tu payez joyeusement le capitaine pour ce bonheur instinctivement ressenti",
        "Tu payées joyeusement le capitaine pour ce bonheur instinctivement ressenti",
        "Tu payés joyeusement le capitaine pour ce bonheur instinctivement ressenti"
    ],
    "correct": 0,
    "explanation": "The text states '<em>Tu paies joyeusement le capitaine pour ce bonheur instinctivement ressenti</em>' - You joyfully pay the captain for this happiness instinctively felt. 'Tu paies' is the correct present tense form of 'payer' (to pay). 'Capitaine' means captain and 'bonheur' means happiness. The distractors test confusion about the correct verb form.",
    "difficulty": "B2",
    "source": "Strategic targeting: capitaine + bonheur + payez → paies + joyeusement + instinctivement",
    "tags": ["payment", "emotions", "navigation"],
    "timeCreated": 1720881353,
    "parentQuestion": 1372
}