{
  "id": 265,
  "audioText": "Quand elle était petite, Marie voulait toujours devenir médecin, mais ses parents préféraient qu'elle étudie le droit.",
  "question": "Quand elle était petite, Marie ______ toujours devenir médecin, mais ses parents préféraient qu'elle étudie le droit.",
  "questionType": "fill-in-the-blank",
  "options": [
    "voulait",
    "veut",
    "voudrait",
    "a voulu"
  ],
  "correct": 0,
  "explanation": "The correct answer is 'voulait' (imperfect tense of vouloir). The context 'Quand elle était petite' (When she was little) indicates a past habitual action, requiring the imperfect tense. 'Voulait' expresses that Marie repeatedly or consistently wanted to become a doctor during her childhood.",
  "difficulty": "B2",
  "source": "Childhood Dreams",
  "tags": ["childhood", "career", "family", "education", "personal-history"],
  "timeCreated": 1751492559
}