{
    "id": 879,
    "audioText": "L'infirmière pensera qu'il est possible de réanimer ce cœur en pratiquant régulièrement des compressions thoraciques.",
    "question": "What does the nurse believe can be accomplished?",
    "questionType": "comprehension",
    "options": [
        "To revive the heart with regular compressions",
        "To perform surgery immediately",
        "To move the patient quickly",
        "To call for more help"
    ],
    "correct": 0,
    "explanation": "The text states '<em>L'infirmière pensera qu'il est possible de réanimer ce cœur en pratiquant régulièrement des compressions</em>' - The nurse will think that it is possible to revive this heart by regularly performing compressions. 'Pensera' is future of penser (to think), 'possible' means possible, 'cœur' means heart, and 'régulièrement' means regularly.",
    "difficulty": "B2",
    "source": "CPR and cardiac resuscitation procedures",
    "tags": ["first-aid", "cpr", "cardiac-care"],
    "timeCreated": 1751788460
}